cythonscreencap2ppm/README.MD
cythonscreencap2ppm/__init__.py
cythonscreencap2ppm/convertimagecy.pyx
cythonscreencap2ppm/convertimagecy_compile.py
cythonscreencap2ppm/requirements.txt
cythonscreencap2ppm/thirdparty.json
cythonscreencap2ppm-0.11.dist-info/LICENSE.rst
cythonscreencap2ppm-0.11.dist-info/METADATA
cythonscreencap2ppm-0.11.dist-info/WHEEL
cythonscreencap2ppm-0.11.dist-info/top_level.txt
cythonscreencap2ppm-0.11.dist-info/RECORD
