Metadata-Version: 2.1
Name: cythonscreencap2ppm
Version: 0.11
Summary: screencap to ppm
Home-page: https://github.com/hansalemaos/cythonscreencap2ppm
Author: Johannes Fischer
Author-email: aulasparticularesdealemaosp@gmail.com
License: MIT
Keywords: Android,instance
Classifier: Development Status :: 4 - Beta
Classifier: Programming Language :: Python :: 3 :: Only
Classifier: Programming Language :: Python :: 3.10
Classifier: Topic :: Software Development :: Libraries :: Python Modules
Classifier: Topic :: Utilities
License-File: LICENSE.rst
Requires-Dist: Cython
Requires-Dist: flatten-any-dict-iterable-or-whatsoever
Requires-Dist: numpy
Requires-Dist: setuptools
Requires-Dist: xmltodict
